sokot/__init__.py
sokot/aggregator.py
sokot/configuration.py
sokot/group.py
sokot/main.py
sokot/requester.py
sokot-0.1.4.dist-info/DESCRIPTION.rst
sokot-0.1.4.dist-info/METADATA
sokot-0.1.4.dist-info/RECORD
sokot-0.1.4.dist-info/WHEEL
sokot-0.1.4.dist-info/entry_points.txt
sokot-0.1.4.dist-info/metadata.json
sokot-0.1.4.dist-info/top_level.txt
