Metadata-Version: 2.0
Name: sokot
Version: 0.1.4
Summary: A tool to get your member's overtime from King of Time for every N weeks.
Home-page: https://github.com/showwin/scrum-overtime-kot
Author: showwin
Author-email: showwin_kmc@yahoo.co.jp
License: Apache Software License
Keywords: overtime king-of-time scrum python tool cli
Platform: UNKNOWN
Classifier: Programming Language :: Python
Classifier: Programming Language :: Python :: 3.4
Classifier: Programming Language :: Python :: 3.5
Classifier: Programming Language :: Python :: 3.6
Requires-Dist: beautifultable (==0.4.0)
Requires-Dist: fire (==0.1.2)
Requires-Dist: requests (==2.18.4)
